{
  "reaction": {
    "lhs": [
      { "state": { "particle": "e", "charge": -1 }, "count": 1 },
      {
        "state": {
          "particle": "H2",
          "charge": 0,
          "electronic": [
            {
              "e": "X",
              "Lambda": 0,
              "S": 0,
              "parity": "g",
              "reflection": "+",
              "summary": "X^1S_g^+",
              "vibrational": [{ "v": 11, "summary": "v=11" }]
            }
          ],
          "id": "H2{X^1S_g^+{v=11}}"
        },
        "count": 1
      }
    ],
    "rhs": [
      { "state": { "particle": "e", "charge": -1 }, "count": 1 },
      {
        "state": {
          "particle": "H2",
          "charge": 0,
          "electronic": [
            {
              "e": "EF",
              "Lambda": 0,
              "S": 0,
              "parity": "g",
              "reflection": "+",
              "summary": "EF^1S_g^+",
              "vibrational": [{ "v": 17, "summary": "v=17" }]
            }
          ],
          "id": "H2{EF^1S_g^+{v=17}}"
        },
        "count": 1
      }
    ],
    "type_tags": ["Electronic", "Vibrational"],
    "reversible": false
  },
  "threshold": 9.67383,
  "data": [
    [9.67383, 0],
    [10, 0.000358919],
    [11, 0.00084405],
    [12, 0.000939813],
    [13, 0.00119893],
    [14, 0.00149836],
    [15, 0.00137771],
    [16, 0.00124563],
    [17, 0.00126673],
    [18, 0.00133047],
    [19, 0.00131435],
    [20, 0.00122592],
    [22, 0.00120111],
    [25, 0.00113163],
    [30, 0.00105061],
    [40, 0.000857106],
    [50, 0.000746613],
    [60, 0.000692802],
    [70, 0.000635175],
    [80, 0.000590749],
    [100, 0.000494545],
    [120, 0.000395203],
    [140, 0.000338067],
    [160, 0.000292553]
  ]
}
