{
  "reaction": {
    "lhs": [
      { "state": { "particle": "e", "charge": -1 }, "count": 1 },
      {
        "state": {
          "particle": "H2",
          "charge": 0,
          "descriptor": { "type": 1, "accuracy": 2, "e": "X", "Lambda": 0, "S": 0, "parity": "g", "v": 2 }
        },
        "count": 1
      }
    ],
    "rhs": [
      { "state": { "particle": "e", "charge": -1 }, "count": 1 },
      {
        "state": {
          "particle": "H2",
          "charge": 0,
          "descriptor": { "type": 1, "accuracy": 2, "e": "a", "Lambda": 0, "S": 1, "parity": "g", "v": 7 }
        },
        "count": 1
      }
    ],
    "type_tags": ["Electronic", "Vibrational"],
    "reversible": false
  },
  "threshold": 12.6396,
  "data": [
    [12.6396, 0],
    [13, 0.0191439],
    [14, 0.0276958],
    [15, 0.0233649],
    [16, 0.0188787],
    [17, 0.0151401],
    [18, 0.0131191],
    [19, 0.0120221],
    [20, 0.0111188],
    [22, 0.00913796],
    [25, 0.00660638],
    [30, 0.00352493],
    [40, 0.00156841],
    [50, 0.000886782],
    [60, 0.000669337],
    [70, 0.000520946],
    [80, 0.000469763],
    [100, 0.000325821],
    [120, 0.000226929],
    [140, 0.000165295],
    [160, 0.000119386]
  ]
}