{
  "reaction": {
    "lhs": [
      { "state": { "particle": "e", "charge": -1 }, "count": 1 },
      {
        "state": {
          "particle": "H2",
          "charge": 0,
          "descriptor": {
            "type": 1,
            "accuracy": 2,
            "e": "X",
            "Lambda": 0,
            "S": 0,
            "parity": "g",
            "v": 12
          }
        },
        "count": 1
      }
    ],
    "rhs": [
      { "state": { "particle": "e", "charge": -1 }, "count": 1 },
      {
        "state": {
          "particle": "H2",
          "charge": 0,
          "descriptor": { "type": 1, "accuracy": 2, "e": "C", "Lambda": 1, "S": 0, "parity": "u", "v": 4 }
        },
        "count": 1
      }
    ],
    "type_tags": ["Electronic", "Vibrational"],
    "reversible": false
  },
  "threshold": 9.08418,
  "data": [
    [9.08418, 0],
    [10, 1.06792e-7],
    [11, 2.22933e-7],
    [12, 3.38627e-7],
    [13, 4.53639e-7],
    [14, 5.67736e-7],
    [15, 6.80685e-7],
    [16, 7.92251e-7],
    [17, 9.02201e-7],
    [18, 0.0000010103],
    [19, 0.00000111632],
    [20, 0.00000122002],
    [22, 0.00000141954],
    [25, 0.00000169559],
    [30, 0.00000207819],
    [40, 0.00000252351],
    [50, 0.00000270146],
    [60, 0.00000283343],
    [70, 0.00000302036],
    [80, 0.00000302092],
    [100, 0.00000290341],
    [120, 0.00000268622],
    [140, 0.00000246859],
    [160, 0.00000228126]
  ]
}