{
  "reaction": {
    "lhs": [
      { "state": { "particle": "e", "charge": -1 }, "count": 1 },
      {
        "state": {
          "particle": "H2",
          "charge": 0,
          "descriptor": {
            "type": 1,
            "accuracy": 2,
            "e": "X",
            "Lambda": 0,
            "S": 0,
            "parity": "g",
            "v": 12
          }
        },
        "count": 1
      }
    ],
    "rhs": [
      { "state": { "particle": "e", "charge": -1 }, "count": 1 },
      {
        "state": {
          "particle": "H2",
          "charge": 0,
          "descriptor": {
            "type": 1,
            "accuracy": 2,
            "e": "Bp",
            "Lambda": 0,
            "S": 0,
            "parity": "u",
            "v": 2
          }
        },
        "count": 1
      }
    ],
    "type_tags": ["Electronic", "Vibrational"],
    "reversible": false
  },
  "threshold": 9.89004,
  "data": [
    [9.89004, 0],
    [10, 2.83691e-11],
    [11, 2.84038e-10],
    [12, 5.39417e-10],
    [13, 7.94264e-10],
    [14, 1.04832e-9],
    [15, 1.30136e-9],
    [16, 1.55312e-9],
    [17, 1.8033e-9],
    [18, 2.0517e-9],
    [19, 2.29806e-9],
    [20, 2.54212e-9],
    [22, 3.02232e-9],
    [25, 3.7191e-9],
    [30, 4.80074e-9],
    [40, 6.55187e-9],
    [50, 7.54275e-9],
    [60, 1.25593e-8],
    [70, 3.93324e-8],
    [80, 7.88519e-8],
    [100, 1.28032e-7],
    [120, 1.48794e-7],
    [140, 1.61523e-7],
    [160, 1.70278e-7]
  ]
}