{
  "reaction": {
    "lhs": [
      { "state": { "particle": "e", "charge": -1 }, "count": 1 },
      {
        "state": {
          "particle": "H2",
          "charge": 0,
          "descriptor": { "type": 1, "accuracy": 2, "e": "X", "Lambda": 0, "S": 0, "parity": "g", "v": 8 }
        },
        "count": 1
      }
    ],
    "rhs": [
      { "state": { "particle": "e", "charge": -1 }, "count": 1 },
      {
        "state": {
          "particle": "H2",
          "charge": 0,
          "descriptor": { "type": 1, "accuracy": 2, "e": "i", "Lambda": 1, "S": 1, "parity": "g", "v": 1 }
        },
        "count": 1
      }
    ],
    "type_tags": ["Electronic", "Vibrational"],
    "reversible": false
  },
  "threshold": 10.8149,
  "data": [
    [10.8149, 0],
    [11, 4.01765e-7],
    [12, 0.0000229895],
    [13, 0.0000325655],
    [14, 0.00000148391],
    [15, 0.00000104615],
    [16, 0.00000423752],
    [17, 0.00000864635],
    [18, 0.0000105605],
    [19, 0.0000115646],
    [20, 0.0000118555],
    [22, 0.0000109849],
    [25, 0.00000767007],
    [30, 0.00000348463],
    [40, 0.00000357736],
    [50, 0.00000256791],
    [60, 0.00000114294],
    [70, 5.19063e-7],
    [80, 2.53137e-7],
    [100, 1.23491e-7],
    [120, 9.90256e-8],
    [140, 8.10171e-8],
    [160, 6.64244e-8]
  ]
}