{
  "reaction": {
    "lhs": [
      { "state": { "particle": "e", "charge": -1 }, "count": 1 },
      {
        "state": {
          "particle": "H2",
          "charge": 0,
          "electronic": [
            {
              "e": "X",
              "Lambda": 0,
              "S": 0,
              "parity": "g",
              "reflection": "+",
              "summary": "X^1S_g^+",
              "vibrational": [{ "v": 14, "summary": "v=14" }]
            }
          ],
          "id": "H2{X^1S_g^+{v=14}}"
        },
        "count": 1
      }
    ],
    "rhs": [
      { "state": { "particle": "e", "charge": -1 }, "count": 1 },
      {
        "state": {
          "particle": "H2",
          "charge": 0,
          "electronic": [
            {
              "e": "EF",
              "Lambda": 0,
              "S": 0,
              "parity": "g",
              "reflection": "+",
              "summary": "EF^1S_g^+",
              "vibrational": [{ "v": 17, "summary": "v=17" }]
            }
          ],
          "id": "H2{EF^1S_g^+{v=17}}"
        },
        "count": 1
      }
    ],
    "type_tags": ["Electronic", "Vibrational"],
    "reversible": false
  },
  "threshold": 9.29233,
  "data": [
    [9.29233, 0],
    [10, 0.00263125],
    [11, 0.00360451],
    [12, 0.00348332],
    [13, 0.00410617],
    [14, 0.00447477],
    [15, 0.00440293],
    [16, 0.00434169],
    [17, 0.00416928],
    [18, 0.00423474],
    [19, 0.00414254],
    [20, 0.00390288],
    [22, 0.00369393],
    [25, 0.00342976],
    [30, 0.00296626],
    [40, 0.0023867],
    [50, 0.00208454],
    [60, 0.00188368],
    [70, 0.00163229],
    [80, 0.00142657],
    [100, 0.0011399],
    [120, 0.00093879],
    [140, 0.000819575],
    [160, 0.000722673]
  ]
}
