{
  "reaction": {
    "lhs": [
      { "state": { "particle": "e", "charge": -1 }, "count": 1 },
      {
        "state": {
          "particle": "H2",
          "charge": 0,
          "electronic": [
            {
              "e": "X",
              "Lambda": 0,
              "S": 0,
              "parity": "g",
              "reflection": "+",
              "summary": "X^1S_g^+",
              "vibrational": [{ "v": 14, "summary": "v=14" }]
            }
          ],
          "id": "H2{X^1S_g^+{v=14}}"
        },
        "count": 1
      }
    ],
    "rhs": [
      { "state": { "particle": "e", "charge": -1 }, "count": 1 },
      {
        "state": {
          "particle": "H2",
          "charge": 0,
          "electronic": [
            {
              "e": "GK",
              "Lambda": 0,
              "S": 0,
              "parity": "g",
              "reflection": "+",
              "summary": "GK^1S_g^+",
              "vibrational": [{ "v": 5, "summary": "v=5" }]
            }
          ],
          "id": "H2{GK^1S_g^+{v=5}}"
        },
        "count": 1
      }
    ],
    "type_tags": ["Electronic", "Vibrational"],
    "reversible": false
  },
  "threshold": 9.93075,
  "data": [
    [9.93075, 0],
    [10, 0.000531128],
    [11, 0.00788051],
    [12, 0.00869341],
    [13, 0.0103576],
    [14, 0.0105386],
    [15, 0.0121257],
    [16, 0.0123931],
    [17, 0.0115381],
    [18, 0.011707],
    [19, 0.0115851],
    [20, 0.0112772],
    [22, 0.0116712],
    [25, 0.0115694],
    [30, 0.0113018],
    [40, 0.00957344],
    [50, 0.00960502],
    [60, 0.00939693],
    [70, 0.00887867],
    [80, 0.00800117],
    [100, 0.00691585],
    [120, 0.00611529],
    [140, 0.00547593],
    [160, 0.00511253]
  ]
}
