{
  "reaction": {
    "lhs": [
      { "state": { "particle": "e", "charge": -1 }, "count": 1 },
      {
        "state": {
          "particle": "H2",
          "charge": 0,
          "electronic": [
            {
              "e": "X",
              "Lambda": 0,
              "S": 0,
              "parity": "g",
              "reflection": "+",
              "summary": "X^1S_g^+",
              "vibrational": [{ "v": 14, "summary": "v=14" }]
            }
          ],
          "id": "H2{X^1S_g^+{v=14}}"
        },
        "count": 1
      }
    ],
    "rhs": [
      { "state": { "particle": "e", "charge": -1 }, "count": 1 },
      {
        "state": {
          "particle": "H2",
          "charge": 0,
          "electronic": [
            {
              "e": "j",
              "Lambda": 2,
              "S": 1,
              "parity": "g",
              "summary": "j^3D_g",
              "vibrational": [{ "v": 16, "summary": "v=16" }]
            }
          ],
          "id": "H2{j^3D_g{v=16}}"
        },
        "count": 1
      }
    ],
    "type_tags": ["Electronic", "Vibrational"],
    "reversible": false
  },
  "threshold": 12.0879,
  "data": [
    [12.0879, 0],
    [13, 6.63806e-9],
    [14, 9.51537e-7],
    [15, 3.87294e-8],
    [16, 9.39345e-9],
    [17, 5.20018e-9],
    [18, 1.8184e-7],
    [19, 5.09886e-7],
    [20, 6.86526e-7],
    [22, 6.18793e-7],
    [25, 3.60885e-7],
    [30, 3.52446e-8],
    [40, 3.59475e-7],
    [50, 3.10979e-7],
    [60, 2.43778e-7],
    [70, 2.24427e-7],
    [80, 2.09832e-7],
    [100, 1.20761e-7],
    [120, 5.45392e-8],
    [140, 4.5563e-8],
    [160, 3.8645e-8]
  ]
}
