{
  "reaction": {
    "lhs": [
      { "state": { "particle": "e", "charge": -1 }, "count": 1 },
      {
        "state": {
          "particle": "H2",
          "charge": 0,
          "electronic": [
            {
              "e": "X",
              "Lambda": 0,
              "S": 0,
              "parity": "g",
              "reflection": "+",
              "summary": "X^1S_g^+",
              "vibrational": [{ "v": 5, "summary": "v=5" }]
            }
          ],
          "id": "H2{X^1S_g^+{v=5}}"
        },
        "count": 1
      }
    ],
    "rhs": [
      { "state": { "particle": "e", "charge": -1 }, "count": 1 },
      {
        "state": {
          "particle": "H2",
          "charge": 0,
          "electronic": [
            {
              "e": "J",
              "Lambda": 2,
              "S": 0,
              "parity": "g",
              "summary": "J^1D_g",
              "vibrational": [{ "v": 6, "summary": "v=6" }]
            }
          ],
          "id": "H2{J^1D_g{v=6}}"
        },
        "count": 1
      }
    ],
    "type_tags": ["Electronic", "Vibrational"],
    "reversible": false
  },
  "threshold": 13.065,
  "data": [
    [13.065, 0],
    [14, 0.0006833],
    [15, 0.00109875],
    [16, 0.00081161],
    [17, 0.000783344],
    [18, 0.000769576],
    [19, 0.000779224],
    [20, 0.000903744],
    [22, 0.00097472],
    [25, 0.000979133],
    [30, 0.00100074],
    [40, 0.000820534],
    [50, 0.000651205],
    [60, 0.000567644],
    [70, 0.000512004],
    [80, 0.000454356],
    [100, 0.000396057],
    [120, 0.000331307],
    [140, 0.000285582],
    [160, 0.000250303]
  ]
}
