{
  "reaction": {
    "lhs": [
      { "state": { "particle": "e", "charge": -1 }, "count": 1 },
      {
        "state": {
          "particle": "H2",
          "charge": 0,
          "electronic": [
            {
              "e": "X",
              "Lambda": 0,
              "S": 0,
              "parity": "g",
              "reflection": "+",
              "summary": "X^1S_g^+",
              "vibrational": [{ "v": 4, "summary": "v=4" }]
            }
          ],
          "id": "H2{X^1S_g^+{v=4}}"
        },
        "count": 1
      }
    ],
    "rhs": [
      { "state": { "particle": "e", "charge": -1 }, "count": 1 },
      {
        "state": {
          "particle": "H2",
          "charge": 0,
          "electronic": [
            {
              "e": "g",
              "Lambda": 0,
              "S": 1,
              "parity": "g",
              "reflection": "+",
              "summary": "g^3S_g^+",
              "vibrational": [{ "v": 0, "summary": "v=0" }]
            }
          ],
          "id": "H2{g^3S_g^+{v=0}}"
        },
        "count": 1
      }
    ],
    "type_tags": ["Electronic", "Vibrational"],
    "reversible": false
  },
  "threshold": 11.9957,
  "data": [
    [11.9957, 0],
    [12, 0.00232803],
    [13, 0.00700555],
    [14, 0.00724907],
    [15, 0.00769261],
    [16, 0.00638745],
    [17, 0.00453338],
    [18, 0.0036555],
    [19, 0.00309882],
    [20, 0.00268539],
    [22, 0.00200806],
    [25, 0.00136918],
    [30, 0.000822948],
    [40, 0.000508109],
    [50, 0.000331839],
    [60, 0.000182107],
    [70, 0.000117961],
    [80, 9.06748e-5],
    [100, 4.63901e-5],
    [120, 2.84363e-5],
    [140, 2.08191e-5],
    [160, 1.50152e-5]
  ]
}
