{
  "reaction": {
    "lhs": [
      { "state": { "particle": "e", "charge": -1 }, "count": 1 },
      {
        "state": {
          "particle": "H2",
          "charge": 0,
          "electronic": [
            {
              "e": "X",
              "Lambda": 0,
              "S": 0,
              "parity": "g",
              "reflection": "+",
              "summary": "X^1S_g^+",
              "vibrational": [{ "v": 0, "summary": "v=0" }]
            }
          ],
          "id": "H2{X^1S_g^+{v=0}}"
        },
        "count": 1
      }
    ],
    "rhs": [
      { "state": { "particle": "e", "charge": -1 }, "count": 1 },
      {
        "state": {
          "particle": "H2",
          "charge": 0,
          "electronic": [
            {
              "e": "I",
              "Lambda": 1,
              "S": 0,
              "parity": "g",
              "summary": "I^1P_g",
              "vibrational": [{ "v": 2, "summary": "v=2" }]
            }
          ],
          "id": "H2{I^1P_g{v=2}}"
        },
        "count": 1
      }
    ],
    "type_tags": ["Electronic", "Vibrational"],
    "reversible": false
  },
  "threshold": 14.3842,
  "data": [
    [14.3842, 0],
    [15, 0.00170606],
    [16, 0.00274969],
    [17, 0.00235037],
    [18, 0.00243458],
    [19, 0.00242709],
    [20, 0.00254568],
    [22, 0.00301169],
    [25, 0.00331655],
    [30, 0.00307093],
    [40, 0.00246434],
    [50, 0.00195488],
    [60, 0.00177096],
    [70, 0.00167427],
    [80, 0.00151376],
    [100, 0.00126078],
    [120, 0.00107174],
    [140, 0.000933028],
    [160, 0.000828856]
  ]
}
