{
  "reaction": {
    "lhs": [
      { "state": { "particle": "e", "charge": -1 }, "count": 1 },
      {
        "state": {
          "particle": "H2",
          "charge": 0,
          "electronic": [
            {
              "e": "X",
              "Lambda": 0,
              "S": 0,
              "parity": "g",
              "reflection": "+",
              "summary": "X^1S_g^+",
              "vibrational": [{ "v": 0, "summary": "v=0" }]
            }
          ],
          "id": "H2{X^1S_g^+{v=0}}"
        },
        "count": 1
      }
    ],
    "rhs": [
      { "state": { "particle": "e", "charge": -1 }, "count": 1 },
      {
        "state": {
          "particle": "H2",
          "charge": 0,
          "electronic": [
            {
              "e": "D",
              "Lambda": 1,
              "S": 0,
              "parity": "u",
              "summary": "D^1P_u",
              "vibrational": [{ "v": 15, "summary": "v=15" }]
            }
          ],
          "id": "H2{D^1P_u{v=15}}"
        },
        "count": 1
      }
    ],
    "type_tags": ["Electronic", "Vibrational"],
    "reversible": false
  },
  "threshold": 16.5215,
  "data": [
    [16.5215, 0],
    [17, 1.28935e-5],
    [18, 3.20371e-5],
    [19, 4.96725e-5],
    [20, 6.26213e-5],
    [22, 7.94531e-5],
    [25, 0.000107591],
    [30, 0.000152631],
    [40, 0.000219202],
    [50, 0.000257643],
    [60, 0.000280475],
    [70, 0.000292162],
    [80, 0.000296248],
    [100, 0.000293885],
    [120, 0.00028424],
    [140, 0.000273571],
    [160, 0.000263201]
  ]
}
