{
  "reaction": {
    "lhs": [
      { "state": { "particle": "e", "charge": -1 }, "count": 1 },
      {
        "state": {
          "particle": "H2",
          "charge": 0,
          "electronic": [
            {
              "e": "X",
              "Lambda": 0,
              "S": 0,
              "parity": "g",
              "reflection": "+",
              "summary": "X^1S_g^+",
              "vibrational": [{ "v": 3, "summary": "v=3" }]
            }
          ],
          "id": "H2{X^1S_g^+{v=3}}"
        },
        "count": 1
      }
    ],
    "rhs": [
      { "state": { "particle": "e", "charge": -1 }, "count": 1 },
      {
        "state": {
          "particle": "H2",
          "charge": 0,
          "electronic": [
            {
              "e": "g",
              "Lambda": 0,
              "S": 1,
              "parity": "g",
              "reflection": "+",
              "summary": "g^3S_g^+",
              "vibrational": [{ "v": 13, "summary": "v=13" }]
            }
          ],
          "id": "H2{g^3S_g^+{v=13}}"
        },
        "count": 1
      }
    ],
    "type_tags": ["Electronic", "Vibrational"],
    "reversible": false
  },
  "threshold": 14.9115,
  "data": [
    [14.9115, 0],
    [15, 1.9411e-5],
    [16, 8.94507e-5],
    [17, 0.000106985],
    [18, 0.000112265],
    [19, 9.62931e-5],
    [20, 8.27758e-5],
    [22, 7.33264e-5],
    [25, 5.78921e-5],
    [30, 3.5565e-5],
    [40, 1.54735e-5],
    [50, 1.10277e-5],
    [60, 1.00624e-5],
    [70, 6.99123e-6],
    [80, 4.30711e-6],
    [100, 3.95188e-6],
    [120, 3.89469e-6],
    [140, 3.78674e-6],
    [160, 3.5274e-6]
  ]
}
