{
  "reaction": {
    "lhs": [
      { "state": { "particle": "e", "charge": -1 }, "count": 1 },
      {
        "state": {
          "particle": "H2",
          "charge": 0,
          "electronic": [
            {
              "e": "X",
              "Lambda": 0,
              "S": 0,
              "parity": "g",
              "reflection": "+",
              "summary": "X^1S_g^+",
              "vibrational": [{ "v": 13, "summary": "v=13" }]
            }
          ],
          "id": "H2{X^1S_g^+{v=13}}"
        },
        "count": 1
      }
    ],
    "rhs": [
      { "state": { "particle": "e", "charge": -1 }, "count": 1 },
      {
        "state": {
          "particle": "H2",
          "charge": 0,
          "electronic": [
            {
              "e": "J",
              "Lambda": 2,
              "S": 0,
              "parity": "g",
              "summary": "J^1D_g",
              "vibrational": [{ "v": 9, "summary": "v=9" }]
            }
          ],
          "id": "H2{J^1D_g{v=9}}"
        },
        "count": 1
      }
    ],
    "type_tags": ["Electronic", "Vibrational"],
    "reversible": false
  },
  "threshold": 11.4922,
  "data": [
    [11.4922, 0],
    [12, 0.0146376],
    [13, 0.0148015],
    [14, 0.0146768],
    [15, 0.0140058],
    [16, 0.0166197],
    [17, 0.0167353],
    [18, 0.0167729],
    [19, 0.0181387],
    [20, 0.0188037],
    [22, 0.0187517],
    [25, 0.0179265],
    [30, 0.0159793],
    [40, 0.0123881],
    [50, 0.0100474],
    [60, 0.00841356],
    [70, 0.0071626],
    [80, 0.00635341],
    [100, 0.00511347],
    [120, 0.00424685],
    [140, 0.00364402],
    [160, 0.00319215]
  ]
}
