{
  "reaction": {
    "lhs": [
      { "state": { "particle": "e", "charge": -1 }, "count": 1 },
      {
        "state": {
          "particle": "H2",
          "charge": 0,
          "electronic": [
            {
              "e": "X",
              "Lambda": 0,
              "S": 0,
              "parity": "g",
              "reflection": "+",
              "summary": "X^1S_g^+",
              "vibrational": [{ "v": 13, "summary": "v=13" }]
            }
          ],
          "id": "H2{X^1S_g^+{v=13}}"
        },
        "count": 1
      }
    ],
    "rhs": [
      { "state": { "particle": "e", "charge": -1 }, "count": 1 },
      {
        "state": {
          "particle": "H2",
          "charge": 0,
          "electronic": [
            {
              "e": "B",
              "Lambda": 0,
              "S": 0,
              "parity": "u",
              "reflection": "+",
              "summary": "B^1S_u^+",
              "vibrational": [{ "v": 11, "summary": "v=11" }]
            }
          ],
          "id": "H2{B^1S_u^+{v=11}}"
        },
        "count": 1
      }
    ],
    "type_tags": ["Electronic", "Vibrational"],
    "reversible": false
  },
  "threshold": 8.3714,
  "data": [
    [8.3714, 0],
    [10, 0.0292948],
    [11, 0.0383096],
    [12, 0.044716],
    [13, 0.049689],
    [14, 0.0537701],
    [15, 0.0571204],
    [16, 0.0598062],
    [17, 0.0618958],
    [18, 0.0634586],
    [19, 0.0645642],
    [20, 0.0652818],
    [22, 0.0658337],
    [25, 0.0654772],
    [30, 0.0647839],
    [40, 0.0631643],
    [50, 0.0608483],
    [60, 0.0582969],
    [70, 0.0557264],
    [80, 0.0530763],
    [100, 0.0480632],
    [120, 0.0435814],
    [140, 0.0396443],
    [160, 0.0362155]
  ]
}
