{
  "reaction": {
    "lhs": [
      { "state": { "particle": "e", "charge": -1 }, "count": 1 },
      {
        "state": {
          "particle": "H2",
          "charge": 0,
          "electronic": [
            {
              "e": "X",
              "Lambda": 0,
              "S": 0,
              "parity": "g",
              "reflection": "+",
              "summary": "X^1S_g^+",
              "vibrational": [{ "v": 13, "summary": "v=13" }]
            }
          ],
          "id": "H2{X^1S_g^+{v=13}}"
        },
        "count": 1
      }
    ],
    "rhs": [
      { "state": { "particle": "e", "charge": -1 }, "count": 1 },
      {
        "state": {
          "particle": "H2",
          "charge": 0,
          "electronic": [
            {
              "e": "H",
              "Lambda": 0,
              "S": 0,
              "parity": "g",
              "reflection": "+",
              "summary": "H^1S_g^+",
              "vibrational": [{ "v": 36, "summary": "v=36" }]
            }
          ],
          "id": "H2{H^1S_g^+{v=36}}"
        },
        "count": 1
      }
    ],
    "type_tags": ["Electronic", "Vibrational"],
    "reversible": false
  },
  "threshold": 11.6823,
  "data": [
    [11.6823, 0],
    [12, 5.80399e-5],
    [13, 0.000129475],
    [14, 0.000158811],
    [15, 0.000158339],
    [16, 0.00015454],
    [17, 0.000153706],
    [18, 0.000159522],
    [19, 0.0001759],
    [20, 0.000194257],
    [22, 0.000205803],
    [25, 0.000206487],
    [30, 0.000197489],
    [40, 0.000159198],
    [50, 0.000132519],
    [60, 0.000118361],
    [70, 0.000104969],
    [80, 8.61296e-5],
    [100, 6.56311e-5],
    [120, 5.25732e-5],
    [140, 4.44767e-5],
    [160, 3.96341e-5]
  ]
}
