{
  "reaction": {
    "lhs": [
      { "state": { "particle": "e", "charge": -1 }, "count": 1 },
      {
        "state": {
          "particle": "H2",
          "charge": 0,
          "electronic": [
            {
              "e": "X",
              "Lambda": 0,
              "S": 0,
              "parity": "g",
              "reflection": "+",
              "summary": "X^1S_g^+",
              "vibrational": [{ "v": 8, "summary": "v=8" }]
            }
          ],
          "id": "H2{X^1S_g^+{v=8}}"
        },
        "count": 1
      }
    ],
    "rhs": [
      { "state": { "particle": "e", "charge": -1 }, "count": 1 },
      {
        "state": {
          "particle": "H2",
          "charge": 0,
          "electronic": [
            {
              "e": "H",
              "Lambda": 0,
              "S": 0,
              "parity": "g",
              "reflection": "+",
              "summary": "H^1S_g^+",
              "vibrational": [{ "v": 9, "summary": "v=9" }]
            }
          ],
          "id": "H2{H^1S_g^+{v=9}}"
        },
        "count": 1
      }
    ],
    "type_tags": ["Electronic", "Vibrational"],
    "reversible": false
  },
  "threshold": 11.999,
  "data": [
    [11.999, 0],
    [12, 0.000297457],
    [13, 0.000549366],
    [14, 0.000772124],
    [15, 0.000902232],
    [16, 0.00099507],
    [17, 0.00111602],
    [18, 0.00125458],
    [19, 0.00139416],
    [20, 0.00151891],
    [22, 0.00171472],
    [25, 0.00174752],
    [30, 0.00142567],
    [40, 0.0011011],
    [50, 0.000956647],
    [60, 0.000838578],
    [70, 0.000765728],
    [80, 0.000732809],
    [100, 0.00058596],
    [120, 0.000483773],
    [140, 0.000410132],
    [160, 0.000353329]
  ]
}
