{
  "reaction": {
    "lhs": [
      { "state": { "particle": "e", "charge": -1 }, "count": 1 },
      {
        "state": {
          "particle": "H2",
          "charge": 0,
          "descriptor": { "type": 1, "accuracy": 2, "e": "X", "Lambda": 0, "S": 0, "parity": "g", "v": 6 }
        },
        "count": 1
      }
    ],
    "rhs": [
      { "state": { "particle": "e", "charge": -1 }, "count": 1 },
      {
        "state": {
          "particle": "H2",
          "charge": 0,
          "descriptor": {
            "type": 1,
            "accuracy": 2,
            "e": "GK",
            "Lambda": 0,
            "S": 0,
            "parity": "g",
            "v": 6
          }
        },
        "count": 1
      }
    ],
    "type_tags": ["Electronic", "Vibrational"],
    "reversible": false
  },
  "threshold": 11.838,
  "data": [
    [11.838, 0],
    [12, 0.0000434515],
    [13, 0.0000794718],
    [14, 0.0000181471],
    [15, 0.0000546953],
    [16, 0.0000644658],
    [17, 0.0000680358],
    [18, 0.00011506],
    [19, 0.000135925],
    [20, 0.000156487],
    [22, 0.000118617],
    [25, 0.0000632515],
    [30, 0.0000802312],
    [40, 0.0000708124],
    [50, 0.0000504369],
    [60, 0.000115554],
    [70, 0.000252298],
    [80, 0.000437879],
    [100, 0.000406824],
    [120, 0.000331866],
    [140, 0.000261776],
    [160, 0.000210013]
  ]
}