{
  "reaction": {
    "lhs": [
      { "state": { "particle": "e", "charge": -1 }, "count": 1 },
      {
        "state": {
          "particle": "H2",
          "charge": 0,
          "electronic": [
            {
              "e": "X",
              "Lambda": 0,
              "S": 0,
              "parity": "g",
              "reflection": "+",
              "summary": "X^1S_g^+",
              "vibrational": [{ "v": 1, "summary": "v=1" }]
            }
          ],
          "id": "H2{X^1S_g^+{v=1}}"
        },
        "count": 1
      }
    ],
    "rhs": [
      { "state": { "particle": "e", "charge": -1 }, "count": 1 },
      {
        "state": {
          "particle": "H2",
          "charge": 0,
          "electronic": [
            {
              "e": "B",
              "Lambda": 0,
              "S": 0,
              "parity": "u",
              "reflection": "+",
              "summary": "B^1S_u^+",
              "vibrational": [{ "v": 5, "summary": "v=5" }]
            }
          ],
          "id": "H2{B^1S_u^+{v=5}}"
        },
        "count": 1
      }
    ],
    "type_tags": ["Electronic", "Vibrational"],
    "reversible": false
  },
  "threshold": 11.4416,
  "data": [
    [11.4416, 0],
    [12, 0.00978719],
    [13, 0.0218909],
    [14, 0.0311385],
    [15, 0.0378433],
    [16, 0.0433612],
    [17, 0.0487318],
    [18, 0.0542651],
    [19, 0.0597002],
    [20, 0.0646066],
    [22, 0.0724057],
    [25, 0.0807884],
    [30, 0.0896598],
    [40, 0.0988388],
    [50, 0.10063],
    [60, 0.100259],
    [70, 0.0988698],
    [80, 0.0967513],
    [100, 0.0910713],
    [120, 0.0845798],
    [140, 0.0784033],
    [160, 0.0727485]
  ]
}
