{
  "reaction": {
    "lhs": [
      { "state": { "particle": "e", "charge": -1 }, "count": 1 },
      {
        "state": {
          "particle": "H2",
          "charge": 0,
          "descriptor": {
            "type": 1,
            "accuracy": 2,
            "e": "X",
            "Lambda": 0,
            "S": 0,
            "parity": "g",
            "v": 13
          }
        },
        "count": 1
      }
    ],
    "rhs": [
      { "state": { "particle": "e", "charge": -1 }, "count": 1 },
      {
        "state": {
          "particle": "H2",
          "charge": 0,
          "descriptor": { "type": 1, "accuracy": 2, "e": "H", "Lambda": 0, "S": 0, "parity": "g", "v": 2 }
        },
        "count": 1
      }
    ],
    "type_tags": ["Electronic", "Vibrational"],
    "reversible": false
  },
  "threshold": 10.1523,
  "data": [
    [10.1523, 0],
    [11, 6.70626e-7],
    [12, 0.000001684],
    [13, 0.00000270768],
    [14, 0.0000030282],
    [15, 0.00000243783],
    [16, 0.00000155062],
    [17, 8.50869e-7],
    [18, 3.40115e-7],
    [19, 1.20334e-7],
    [20, 2.33004e-7],
    [22, 0.00000101914],
    [25, 0.00000126953],
    [30, 4.97623e-8],
    [40, 1.35827e-7],
    [50, 5.45366e-7],
    [60, 3.24928e-7],
    [70, 2.07053e-8],
    [80, 1.44356e-9],
    [100, 1.17383e-8],
    [120, 4.85191e-9],
    [140, 1.09485e-8],
    [160, 6.40416e-8]
  ]
}