{
  "reaction": {
    "lhs": [
      { "state": { "particle": "e", "charge": -1 }, "count": 1 },
      {
        "state": {
          "particle": "H2",
          "charge": 0,
          "descriptor": {
            "type": 1,
            "accuracy": 2,
            "e": "X",
            "Lambda": 0,
            "S": 0,
            "parity": "g",
            "v": 13
          }
        },
        "count": 1
      }
    ],
    "rhs": [
      { "state": { "particle": "e", "charge": -1 }, "count": 1 },
      {
        "state": {
          "particle": "H2",
          "charge": 0,
          "descriptor": { "type": 1, "accuracy": 2, "e": "c", "Lambda": 1, "S": 1, "parity": "u", "v": 6 }
        },
        "count": 1
      }
    ],
    "type_tags": ["Electronic", "Vibrational"],
    "reversible": false
  },
  "threshold": 8.90962,
  "data": [
    [8.90962, 0],
    [10, 0.0000486494],
    [11, 0.0000533407],
    [12, 0.000120839],
    [13, 0.000136059],
    [14, 0.0000469388],
    [15, 0.0000209234],
    [16, 0.00000871368],
    [17, 0.00000480542],
    [18, 0.00000450152],
    [19, 0.00000439063],
    [20, 0.00000437106],
    [22, 0.00000413382],
    [25, 0.00000320748],
    [30, 0.00000153249],
    [40, 1.23668e-7],
    [50, 1.31696e-7],
    [60, 1.58374e-7],
    [70, 2.24947e-7],
    [80, 2.72869e-7],
    [100, 2.05579e-7],
    [120, 1.20461e-7],
    [140, 8.91308e-8],
    [160, 6.56015e-8]
  ]
}