{
  "reaction": {
    "lhs": [
      { "state": { "particle": "e", "charge": -1 }, "count": 1 },
      {
        "state": {
          "particle": "H2",
          "charge": 0,
          "descriptor": { "type": 1, "accuracy": 2, "e": "X", "Lambda": 0, "S": 0, "parity": "g", "v": 1 }
        },
        "count": 1
      }
    ],
    "rhs": [
      { "state": { "particle": "e", "charge": -1 }, "count": 1 },
      {
        "state": {
          "particle": "H2",
          "charge": 0,
          "descriptor": {
            "type": 1,
            "accuracy": 2,
            "e": "H",
            "Lambda": 0,
            "S": 0,
            "parity": "g",
            "v": 33
          }
        },
        "count": 1
      }
    ],
    "type_tags": ["Electronic", "Vibrational"],
    "reversible": false
  },
  "threshold": 15.4711,
  "data": [
    [15.4711, 0],
    [16, 0.000164071],
    [17, 0.000252123],
    [18, 0.000279042],
    [19, 0.00025445],
    [20, 0.000219958],
    [22, 0.000187175],
    [25, 0.000175168],
    [30, 0.000184643],
    [40, 0.000183091],
    [50, 0.000172722],
    [60, 0.000166184],
    [70, 0.000163353],
    [80, 0.00016251],
    [100, 0.000151843],
    [120, 0.000144326],
    [140, 0.000134845],
    [160, 0.000125033]
  ]
}