{
  "reaction": {
    "lhs": [
      { "state": { "particle": "e", "charge": -1 }, "count": 1 },
      {
        "state": {
          "particle": "H2",
          "charge": 0,
          "descriptor": { "type": 1, "accuracy": 2, "e": "X", "Lambda": 0, "S": 0, "parity": "g", "v": 1 }
        },
        "count": 1
      }
    ],
    "rhs": [
      { "state": { "particle": "e", "charge": -1 }, "count": 1 },
      {
        "state": {
          "particle": "H2",
          "charge": 0,
          "descriptor": {
            "type": 1,
            "accuracy": 2,
            "e": "B",
            "Lambda": 0,
            "S": 0,
            "parity": "u",
            "v": 12
          }
        },
        "count": 1
      }
    ],
    "type_tags": ["Electronic", "Vibrational"],
    "reversible": false
  },
  "threshold": 12.3576,
  "data": [
    [12.3576, 0],
    [13, 0.00223982],
    [14, 0.00451431],
    [15, 0.00634288],
    [16, 0.00778515],
    [17, 0.00899136],
    [18, 0.0101044],
    [19, 0.0111895],
    [20, 0.0122288],
    [22, 0.014021],
    [25, 0.0159958],
    [30, 0.0181755],
    [40, 0.0204098],
    [50, 0.0210357],
    [60, 0.0211057],
    [70, 0.0208726],
    [80, 0.0204631],
    [100, 0.019346],
    [120, 0.0180557],
    [140, 0.01681],
    [160, 0.0156515]
  ]
}