{
  "reaction": {
    "lhs": [
      { "state": { "particle": "e", "charge": -1 }, "count": 1 },
      {
        "state": {
          "particle": "H2",
          "charge": 0,
          "electronic": [
            {
              "e": "X",
              "Lambda": 0,
              "S": 0,
              "parity": "g",
              "reflection": "+",
              "summary": "X^1S_g^+",
              "vibrational": [{ "v": 7, "summary": "v=7" }]
            }
          ],
          "id": "H2{X^1S_g^+{v=7}}"
        },
        "count": 1
      }
    ],
    "rhs": [
      { "state": { "particle": "e", "charge": -1 }, "count": 1 },
      {
        "state": {
          "particle": "H2",
          "charge": 0,
          "electronic": [
            {
              "e": "g",
              "Lambda": 0,
              "S": 1,
              "parity": "g",
              "reflection": "+",
              "summary": "g^3S_g^+",
              "vibrational": [{ "v": 17, "summary": "v=17" }]
            }
          ],
          "id": "H2{g^3S_g^+{v=17}}"
        },
        "count": 1
      }
    ],
    "type_tags": ["Electronic", "Vibrational"],
    "reversible": false
  },
  "threshold": 13.5426,
  "data": [
    [13.5426, 0],
    [14, 3.07936e-5],
    [15, 4.92327e-5],
    [16, 5.07194e-5],
    [17, 5.09326e-5],
    [18, 4.53073e-5],
    [19, 3.38772e-5],
    [20, 2.48105e-5],
    [22, 1.66443e-5],
    [25, 1.06235e-5],
    [30, 7.25738e-6],
    [40, 4.44269e-6],
    [50, 2.8779e-6],
    [60, 1.52777e-6],
    [70, 1.00491e-6],
    [80, 8.1211e-7],
    [100, 4.34673e-7],
    [120, 2.63248e-7],
    [140, 1.89896e-7],
    [160, 1.34117e-7]
  ]
}
