{
  "reaction": {
    "lhs": [
      { "state": { "particle": "e", "charge": -1 }, "count": 1 },
      {
        "state": {
          "particle": "H2",
          "charge": 0,
          "descriptor": {
            "type": 1,
            "accuracy": 2,
            "e": "X",
            "Lambda": 0,
            "S": 0,
            "parity": "g",
            "v": 10
          }
        },
        "count": 1
      }
    ],
    "rhs": [
      { "state": { "particle": "e", "charge": -1 }, "count": 1 },
      {
        "state": {
          "particle": "H2",
          "charge": 0,
          "descriptor": {
            "type": 1,
            "accuracy": 2,
            "e": "d",
            "Lambda": 1,
            "S": 1,
            "parity": "u",
            "v": 16
          }
        },
        "count": 1
      }
    ],
    "type_tags": ["Electronic", "Vibrational"],
    "reversible": false
  },
  "threshold": 12.6559,
  "data": [
    [12.6559, 0],
    [13, 0.00026522],
    [14, 0.000250725],
    [15, 0.000232769],
    [16, 0.000221457],
    [17, 0.000210562],
    [18, 0.000194565],
    [19, 0.000176839],
    [20, 0.000161687],
    [22, 0.000138875],
    [25, 0.000111158],
    [30, 0.0000759912],
    [40, 0.0000359768],
    [50, 0.0000223994],
    [60, 0.0000178369],
    [70, 0.000012972],
    [80, 0.00000992805],
    [100, 0.00000514328],
    [120, 0.00000278382],
    [140, 0.00000199617],
    [160, 0.00000139474]
  ]
}