{
  "reaction": {
    "lhs": [
      { "state": { "particle": "e", "charge": -1 }, "count": 1 },
      {
        "state": {
          "particle": "H2",
          "charge": 0,
          "descriptor": {
            "type": 1,
            "accuracy": 2,
            "e": "X",
            "Lambda": 0,
            "S": 0,
            "parity": "g",
            "v": 10
          }
        },
        "count": 1
      }
    ],
    "rhs": [
      { "state": { "particle": "e", "charge": -1 }, "count": 1 },
      {
        "state": {
          "particle": "H2",
          "charge": 0,
          "descriptor": { "type": 1, "accuracy": 2, "e": "B", "Lambda": 0, "S": 0, "parity": "u", "v": 5 }
        },
        "count": 1
      }
    ],
    "type_tags": ["Electronic", "Vibrational"],
    "reversible": false
  },
  "threshold": 8.0949,
  "data": [
    [8.0949, 0],
    [10, 0.237785],
    [11, 0.297838],
    [12, 0.335709],
    [13, 0.361908],
    [14, 0.382818],
    [15, 0.399887],
    [16, 0.413495],
    [17, 0.42402],
    [18, 0.431833],
    [19, 0.437309],
    [20, 0.440822],
    [22, 0.443421],
    [25, 0.441961],
    [30, 0.441126],
    [40, 0.438643],
    [50, 0.429477],
    [60, 0.415355],
    [70, 0.398509],
    [80, 0.379769],
    [100, 0.344365],
    [120, 0.313081],
    [140, 0.285556],
    [160, 0.261464]
  ]
}