{
  "reaction": {
    "lhs": [
      { "state": { "particle": "e", "charge": -1 }, "count": 1 },
      {
        "state": {
          "particle": "H2",
          "charge": 0,
          "descriptor": {
            "type": 1,
            "accuracy": 2,
            "e": "X",
            "Lambda": 0,
            "S": 0,
            "parity": "g",
            "v": 10
          }
        },
        "count": 1
      }
    ],
    "rhs": [
      { "state": { "particle": "e", "charge": -1 }, "count": 1 },
      {
        "state": {
          "particle": "H2",
          "charge": 0,
          "descriptor": {
            "type": 1,
            "accuracy": 2,
            "e": "H",
            "Lambda": 0,
            "S": 0,
            "parity": "g",
            "v": 10
          }
        },
        "count": 1
      }
    ],
    "type_tags": ["Electronic", "Vibrational"],
    "reversible": false
  },
  "threshold": 11.5056,
  "data": [
    [11.5056, 0],
    [12, 7.47037e-9],
    [13, 1.39903e-8],
    [14, 1.77675e-8],
    [15, 1.90809e-8],
    [16, 2.01817e-8],
    [17, 2.16942e-8],
    [18, 2.32628e-8],
    [19, 2.4499e-8],
    [20, 2.50938e-8],
    [22, 2.48338e-8],
    [25, 2.50476e-8],
    [30, 2.65866e-8],
    [40, 2.37025e-8],
    [50, 2.05317e-8],
    [60, 1.88755e-8],
    [70, 1.74678e-8],
    [80, 1.55228e-8],
    [100, 1.25871e-8],
    [120, 1.05649e-8],
    [140, 9.14866e-9],
    [160, 8.11378e-9]
  ]
}